setup.py
mysqldbModel.egg-info/PKG-INFO
mysqldbModel.egg-info/SOURCES.txt
mysqldbModel.egg-info/dependency_links.txt
mysqldbModel.egg-info/requires.txt
mysqldbModel.egg-info/top_level.txt
mysqldb_model/__init__.py
mysqldb_model/myMysqldb.py