Metadata-Version: 1.0
Name: mysqldbModel
Version: 1.1.0
Summary: mongodbModel
Home-page: UNKNOWN
Author: donglidunyin
Author-email: donglidunyin@163.com
License: UNKNOWN
Platform: UNKNOWN
